dbnet_crnn/__init__.py
dbnet_crnn/image_text.py
dbnet_crnn/ppocr/__init__.py
dbnet_crnn/ppocr/db_post_process.py
dbnet_crnn/ppocr/db_process.py
dbnet_crnn/ppocr/utils/__init__.py
dbnet_crnn/ppocr/utils/character.py
dbnet_crnn/tools/__init__.py
dbnet_crnn/tools/predict_det.py
dbnet_crnn/tools/predict_rec.py
dbnet_crnn/tools/utility.py
service/__about__.py
service/__init__.py
service/image_diff.py
service/image_merge.py
service/image_similar.py
service/image_text.py
service/image_utils.py
vision_ui-2.1.0.data/data/dbnet_crnn/model/det/model
vision_ui-2.1.0.data/data/dbnet_crnn/model/det/params
vision_ui-2.1.0.data/data/dbnet_crnn/model/rec/model
vision_ui-2.1.0.data/data/dbnet_crnn/model/rec/params
vision_ui-2.1.0.data/data/dbnet_crnn/ppocr/utils/keys.txt
vision_ui-2.1.0.dist-info/LICENSE
vision_ui-2.1.0.dist-info/METADATA
vision_ui-2.1.0.dist-info/WHEEL
vision_ui-2.1.0.dist-info/top_level.txt
vision_ui-2.1.0.dist-info/RECORD
