Metadata-Version: 2.1
Name: vision-ui
Version: 2.1.0
Summary: A line-oriented image diff algorithm.
Home-page: https://github.com/Meituan-Dianping/vision-ui
Author: tech@meituan.com
Author-email: tech@meituan.com
License: MIT
Keywords: A line-oriented image diff algorithm
Platform: UNKNOWN
Classifier: Development Status :: 3 - Alpha
Classifier: Programming Language :: Python :: 2.7
Classifier: Programming Language :: Python :: 3.4
Classifier: Programming Language :: Python :: 3.5
Classifier: Programming Language :: Python :: 3.6
Classifier: Programming Language :: Python :: 3.7
Requires-Python: >=2.7, !=3.0.*, !=3.1.*, !=3.2.*, !=3.3.*, <4
Requires-Dist: opencv-python (==4.2.0.32)
Requires-Dist: numpy (==1.19.1)
Requires-Dist: Flask (==1.0.2)
Requires-Dist: Flask-Cors (==3.0.7)
Requires-Dist: pillow (==6.2.0)
Requires-Dist: paddlepaddle (==1.8.4)
Requires-Dist: gunicorn (==20.0.4)
Requires-Dist: onnxruntime (==1.4.0)
Requires-Dist: pyclipper (==1.2.0)
Requires-Dist: shapely (==1.7.0)
